trendline/__init__.py
trendline/trendline.py
trendline-0.2.dist-info/LICENSE
trendline-0.2.dist-info/METADATA
trendline-0.2.dist-info/WHEEL
trendline-0.2.dist-info/top_level.txt
trendline-0.2.dist-info/RECORD
